nanomock/__init__.py
nanomock/debug.py
nanomock/main.py
nanomock/nanomock_manager.py
nanomock/docker/__init__.py
nanomock/docker/interface.py
nanomock/docker/linux.py
nanomock/docker/macos.py
nanomock/docker/mixin.py
nanomock/docker/windows.py
nanomock/internal/__init__.py
nanomock/internal/dependency_checker.py
nanomock/internal/feature_toggle.py
nanomock/internal/nl_block_tools.py
nanomock/internal/nl_initialise.py
nanomock/internal/utils.py
nanomock/internal/data/__init__.py
nanomock/internal/data/services/__init__.py
nanomock/internal/data/services/custom_Dockerfile
nanomock/internal/data/services/default_config-log.toml
nanomock/internal/data/services/default_config-node.toml
nanomock/internal/data/services/default_config-node_voting-disabled.toml
nanomock/internal/data/services/default_config-rpc.toml
nanomock/internal/data/services/default_docker-compose.yml
nanomock/internal/data/services/rust_docker-compose.yml
nanomock/internal/data/services/nanocap/__init__.py
nanomock/internal/data/services/nanocap/nanocap-compose.yml
nanomock/internal/data/services/nanocap/nanocap.config
nanomock/internal/data/services/nanolooker/Dockerfile
nanomock/internal/data/services/nanolooker/__init__.py
nanomock/internal/data/services/nanolooker/default_docker-compose.yml
nanomock/internal/data/services/nanomonitor/__init__.py
nanomock/internal/data/services/nanomonitor/default_config.php
nanomock/internal/data/services/nanomonitor/default_docker-compose.yml
nanomock/internal/data/services/nanoticker/Dockerfile
nanomock/internal/data/services/nanoticker/__init__.py
nanomock/internal/data/services/nanoticker/default_docker-compose.yml
nanomock/internal/data/services/nanovotevisu/Dockerfile
nanomock/internal/data/services/nanovotevisu/__init__.py
nanomock/internal/data/services/nanovotevisu/default_docker-compose.yml
nanomock/internal/data/services/nanovotevisu/environment.prod.ts
nanomock/internal/data/services/promexporter/Dockerfile
nanomock-0.0.25.dist-info/METADATA
nanomock-0.0.25.dist-info/WHEEL
nanomock-0.0.25.dist-info/entry_points.txt
nanomock-0.0.25.dist-info/top_level.txt
nanomock-0.0.25.dist-info/RECORD
