Metadata-Version: 2.1
Name: nanomock
Version: 0.0.25
Summary: Create local dockerized nano-currency networks
Home-page: https://github.com/gr0vity-dev/nanomock
Author: gr0vity
Requires-Dist: pyyaml
Requires-Dist: tomli_w
Requires-Dist: tomli
Requires-Dist: oyaml
Requires-Dist: nano_lib_py
Requires-Dist: extradict
Requires-Dist: nanorpc
Requires-Dist: bitmath
